odoo/addons/stock_serial_batch_receive/README.rst
odoo/addons/stock_serial_batch_receive/__init__.py
odoo/addons/stock_serial_batch_receive/__manifest__.py
odoo/addons/stock_serial_batch_receive/i18n/stock_serial_batch_receive.pot
odoo/addons/stock_serial_batch_receive/models/__init__.py
odoo/addons/stock_serial_batch_receive/models/stock_move.py
odoo/addons/stock_serial_batch_receive/readme/CONTRIBUTORS.rst
odoo/addons/stock_serial_batch_receive/readme/DESCRIPTION.rst
odoo/addons/stock_serial_batch_receive/readme/ROADMAP.rst
odoo/addons/stock_serial_batch_receive/static/description/icon.png
odoo/addons/stock_serial_batch_receive/static/description/index.html
odoo/addons/stock_serial_batch_receive/tests/__init__.py
odoo/addons/stock_serial_batch_receive/tests/test_stock_serial_batch.py
odoo/addons/stock_serial_batch_receive/views/stock_move.xml
odoo/addons/stock_serial_batch_receive/wizard/__init__.py
odoo/addons/stock_serial_batch_receive/wizard/stock_move_line_serial_generator.py
odoo/addons/stock_serial_batch_receive/wizard/stock_move_line_serial_generator.xml
odoo12_addon_stock_serial_batch_receive-12.0.1.0.1.dist-info/METADATA
odoo12_addon_stock_serial_batch_receive-12.0.1.0.1.dist-info/WHEEL
odoo12_addon_stock_serial_batch_receive-12.0.1.0.1.dist-info/top_level.txt
odoo12_addon_stock_serial_batch_receive-12.0.1.0.1.dist-info/RECORD
